{
  "cohorts": [
    {
      "cohort": "dscli worker log tail command",
      "cohortOrder": 1,
      "area": "backend",
      "files": [
        "cli/command.py",
        "cli/logs.py",
        "cli/tests/test_logs.py",
        "docs/superpowers/plans/2026-07-15-dscli-logs.md",
        "docs/superpowers/specs/2026-07-15-dscli-logs-design.md"
      ],
      "layers": [
        {
          "layer": "other",
          "order": 1,
          "area": "docs",
          "title": "Define Operator Workflow",
          "summary": "The design and plan documents establish the intended operator workflow before code is introduced. They specify a local, read-only `dscli logs -w <host:port> [-n N]` command that resolves workers using the existing `-worker_address=` signal and tails the corresponding local log file.",
          "files": [
            "docs/superpowers/plans/2026-07-15-dscli-logs.md",
            "docs/superpowers/specs/2026-07-15-dscli-logs-design.md"
          ],
          "diff": "+Add a read-only `dscli logs` subcommand that prints the last N lines of a\n+datasystem worker's log file, selected by the worker's address.\n+\n+1. **Add `cli/logs.py`** -- a `Command(BaseCommand)` subclass:\n+   - `name`/`description`, and `add_arguments` for `-w/--worker_address`\n+     (required) and `-n/--lines` (default 100).\n+   - `run(args)`: resolve the worker by address, locate its log file under the\n+     worker log directory, and print the last N lines to stdout.\n+\n+**Out of scope (YAGNI):**\n+- Follow mode (`tail -f` / `-f`).\n+- Multi-worker or remote-host aggregation.\n+- Filtering / grep (operators can pipe to `grep`)."
        },
        {
          "layer": "backend",
          "order": 2,
          "area": "backend",
          "title": "Implement Logs Command",
          "summary": "The backend CLI layer adds a `BaseCommand` subclass that accepts a worker address and optional tail length. It checks for a matching running worker with `pgrep`, warns if absent, then shells out to `tail` against the expected worker log path and prints stdout.",
          "files": [
            "cli/logs.py"
          ],
          "diff": "+class Command(BaseCommand):\n+    \"\"\"Print the last N lines of a worker's log file to stdout.\"\"\"\n+\n+    name = \"logs\"\n+    description = \"print recent log lines for a worker service\"\n+\n+    def add_arguments(self, parser):\n+        parser.add_argument(\n+            \"-w\", \"--worker_address\", metavar=\"ADDR\", required=True,\n+            help=\"address (host:port) of the worker whose log to print\",\n+        )\n+        parser.add_argument(\n+            \"-n\", \"--lines\", metavar=\"N\", default=_DEFAULT_LINES,\n+            help=\"number of trailing log lines to print\",\n+        )\n+\n+    def run(self, args):\n+        address = args.worker_address\n+        if self.find_worker_pid(address) is None:\n+            self.logger.warning(f\"No running worker @ {address}; showing last log\")\n+\n+        log_path = os.path.join(_LOG_DIR, f\"{address}.log\")\n+        result = subprocess.run(\n+            f\"tail -n {args.lines} {log_path}\",\n+            shell=True, capture_output=True, text=True,\n+        )"
        },
        {
          "layer": "api",
          "order": 3,
          "area": "backend",
          "title": "Register Subcommand",
          "summary": "After the command implementation exists, the CLI dispatcher exposes it by adding `logs` to the module list. This makes the new command available through the existing `dscli` command-loading path without changing existing command signatures.",
          "files": [
            "cli/command.py"
          ],
          "diff": "         \"stop\",\n         \"up\",\n         \"down\",\n+        \"logs\",\n         \"runscript\",\n         \"generate_helm_chart\",\n         \"generate_cpp_template\","
        },
        {
          "layer": "tests",
          "order": 4,
          "area": "tests",
          "title": "Cover Primary Path",
          "summary": "The test layer mocks worker discovery and the tail subprocess so the command can be exercised without a real worker or log file. It verifies that a successful tail returns `BaseCommand.SUCCESS`, covering the basic running-worker success path.",
          "files": [
            "cli/tests/test_logs.py"
          ],
          "diff": "+class TestLogsCommand(unittest.TestCase):\n+    \"\"\"Tests for :class:`yr.datasystem.cli.logs.Command`.\"\"\"\n+\n+    @mock.patch(\"yr.datasystem.cli.logs.subprocess.run\")\n+    @mock.patch.object(logs.Command, \"find_worker_pid\", return_value=4321)\n+    def test_run_prints_recent_lines(self, _mock_pid, mock_run):\n+        \"\"\"A running worker's log tail is printed and the command succeeds.\"\"\"\n+        mock_run.return_value = mock.Mock(returncode=0, stdout=\"a\\nb\\nc\\n\", stderr=\"\")\n+\n+        cmd = logs.Command()\n+        args = mock.Mock(worker_address=\"127.0.0.1:31501\", lines=100)\n+        rc = cmd.run(args)\n+\n+        self.assertEqual(rc, logs.BaseCommand.SUCCESS)"
        }
      ],
      "bcFindings": []
    }
  ],
  "summary": "This PR adds a read-only `dscli logs` subcommand that locates a worker by address and prints recent lines from its local log file, with focused unit coverage and design documentation.",
  "risk_band": "Low"
}
