{
  "legs": [
    {
      "leg": "spec-solves-issue",
      "verdict": "n/a",
      "scope": {},
      "summary": "Adherence evidence was not available, so no source verdict or scope was present for this leaf."
    },
    {
      "leg": "plan-implements-spec",
      "verdict": "n/a",
      "scope": {},
      "summary": "Adherence evidence was not available, so no source verdict or scope was present for this leaf."
    },
    {
      "leg": "code-implements-plan",
      "verdict": "n/a",
      "scope": {},
      "summary": "Adherence evidence was not available, so no source verdict or scope was present for this leaf."
    },
    {
      "leg": "mm-compliance",
      "verdict": "diverges",
      "scope": {},
      "summary": "MM compliance evidence reported divergence. The input included 2 graded divergence findings."
    },
    {
      "leg": "docs-updated-appropriately",
      "verdict": "n/a",
      "scope": {},
      "summary": "Consistency evidence was not available, so no source verdict or scope was present for this leaf."
    },
    {
      "leg": "tests-updated-appropriately",
      "verdict": "n/a",
      "scope": {},
      "summary": "Consistency evidence was not available, so no source verdict or scope was present for this leaf."
    },
    {
      "leg": "security",
      "verdict": "LOCKED_VIOLATION",
      "scope": {},
      "summary": "Security evidence reported LOCKED_VIOLATION. The input included 3 graded locked or blocking security findings."
    }
  ],
  "examined": []
}
